<odoo>
    <data>
        <record id="res_partner_bank_form_view_inherited" model="ir.ui.view">
            <field name="name">res.partner.bank.form.view.inherited</field>
            <field name="model">res.partner.bank</field>
            <field name="inherit_id" ref="base.view_partner_bank_form" />
            <field name="arch" type="xml">
                <xpath expr="//field[@name='partner_id']" position="after">
                    <field name='from_type' />
                    <field name='card_code' />
                </xpath>
            </field>
        </record>
    </data>
</odoo>